GLMTopic/__init__.py
GLMTopic/data/hit_stopwords.txt
glmtopic-0.1.1.dist-info/licenses/LICENSE
glmtopic-0.1.1.dist-info/METADATA
glmtopic-0.1.1.dist-info/WHEEL
glmtopic-0.1.1.dist-info/top_level.txt
glmtopic-0.1.1.dist-info/RECORD
