Metadata-Version: 2.4
Name: GLMTopic
Version: 0.1.1
Summary: Topic modeling with GLM embeddings
Home-page: https://github.com/yourusername/GLMTopic
Author: Junjie Chen, Wenqi Liao, Weisi Chen
Author-email: example@example.com
Classifier: Programming Language :: Python :: 3
Classifier: License :: OSI Approved :: MIT License
Classifier: Operating System :: OS Independent
Requires-Python: >=3.6
License-File: LICENSE
Requires-Dist: torch
Requires-Dist: scikit-learn
Requires-Dist: sentence-transformers
Requires-Dist: pandas
Requires-Dist: tqdm
Requires-Dist: umap-learn
Requires-Dist: hdbscan
Requires-Dist: zhipuai
Requires-Dist: numpy
Requires-Dist: plotly
Requires-Dist: matplotlib
Requires-Dist: jieba
Requires-Dist: wordcloud
Dynamic: author
Dynamic: author-email
Dynamic: classifier
Dynamic: description
Dynamic: description-content-type
Dynamic: home-page
Dynamic: license-file
Dynamic: requires-dist
Dynamic: requires-python
Dynamic: summary
